MANIFEST.in
README.rst
setup.py
docs/Makefile
docs/bash_completion
docs/conf.py
docs/config.template
docs/configure.rst
docs/customize.rst
docs/global.inc
docs/index.rst
docs/install.rst
docs/playbooks.rst
docs/usage.rst
docs/api/elasticluster.rst
docs/api/index.rst
docs/api/makehier.sh
docs/api/elasticluster/cluster.rst
docs/api/elasticluster/conf.rst
docs/api/elasticluster/exceptions.rst
docs/api/elasticluster/gc3_config.rst
docs/api/elasticluster/helpers.rst
docs/api/elasticluster/main.rst
docs/api/elasticluster/module.rst
docs/api/elasticluster/providers.rst
docs/api/elasticluster/repository.rst
docs/api/elasticluster/subcommands.rst
docs/api/elasticluster/providers/ansible_provider.rst
docs/api/elasticluster/providers/ec2_boto.rst
docs/api/elasticluster/providers/gce.rst
docs/doctrees/configure.doctree
docs/doctrees/customize.doctree
docs/doctrees/environment.pickle
docs/doctrees/index.doctree
docs/doctrees/install.doctree
docs/doctrees/playbooks.doctree
docs/doctrees/usage.doctree
docs/doctrees/api/elasticluster.doctree
docs/doctrees/api/index.doctree
docs/doctrees/api/elasticluster/cluster.doctree
docs/doctrees/api/elasticluster/conf.doctree
docs/doctrees/api/elasticluster/exceptions.doctree
docs/doctrees/api/elasticluster/gc3_config.doctree
docs/doctrees/api/elasticluster/helpers.doctree
docs/doctrees/api/elasticluster/main.doctree
docs/doctrees/api/elasticluster/module.doctree
docs/doctrees/api/elasticluster/providers.doctree
docs/doctrees/api/elasticluster/repository.doctree
docs/doctrees/api/elasticluster/subcommands.doctree
docs/doctrees/api/elasticluster/providers/ansible_provider.doctree
docs/doctrees/api/elasticluster/providers/ec2_boto.doctree
docs/doctrees/api/elasticluster/providers/gce.doctree
docs/html/.buildinfo
docs/html/configure.html
docs/html/customize.html
docs/html/genindex.html
docs/html/index.html
docs/html/install.html
docs/html/objects.inv
docs/html/playbooks.html
docs/html/py-modindex.html
docs/html/search.html
elasticluster.egg-info/PKG-INFO
elasticluster.egg-info/SOURCES.txt
elasticluster.egg-info/dependency_links.txt
elasticluster.egg-info/entry_points.txt
elasticluster.egg-info/requires.txt
elasticluster.egg-info/top_level.txt
